libsocks/__init__.py
libsocks/context.py
libsocks/utils.py
libsocks/core/__init__.py
libsocks/core/constants.py
libsocks/core/decorators.py
libsocks/core/exceptions.py
libsocks/core/impl.py
libsocks/core/meta.py
libsocks/core/socks4.py
libsocks/core/socks5.py
libsocks/helpers/__init__.py
libsocks/helpers/asyncio.py
libsocks/helpers/sync.py
libsocks-0.0.2.dist-info/DESCRIPTION.rst
libsocks-0.0.2.dist-info/METADATA
libsocks-0.0.2.dist-info/RECORD
libsocks-0.0.2.dist-info/WHEEL
libsocks-0.0.2.dist-info/metadata.json
libsocks-0.0.2.dist-info/top_level.txt
